MANIFEST.in
README.rst
setup.cfg
setup.py
fcm_django/__init__.py
fcm_django/admin.py
fcm_django/apps.py
fcm_django/fcm.py
fcm_django/fields.py
fcm_django/models.py
fcm_django/settings.py
fcm_django/api/__init__.py
fcm_django/api/rest_framework.py
fcm_django/api/tastypie.py
fcm_django/management/__init__.py
fcm_django/management/commands/__init__.py
fcm_django/migrations/0001_initial.py
fcm_django/migrations/0002_auto_20160808_1645.py
fcm_django/migrations/0003_auto_20170313_1314.py
fcm_django/migrations/0004_auto_20181128_1642.py
fcm_django/migrations/0005_auto_20170808_1145.py
fcm_django/migrations/__init__.py
mushriq_fcm_django.egg-info/PKG-INFO
mushriq_fcm_django.egg-info/SOURCES.txt
mushriq_fcm_django.egg-info/dependency_links.txt
mushriq_fcm_django.egg-info/requires.txt
mushriq_fcm_django.egg-info/top_level.txt