Metadata-Version: 1.1
Name: mushriq-fcm-django
Version: 0.3.4
Summary: Send push notifications to mobile devices & browsers through FCM in Django.
Home-page: https://github.com/ysinjab/fcm-django
Author: ysinjab
Author-email: ysinjab@gmail.com
License: UNKNOWN
Download-URL: https://github.com/ysinjab/fcm-django/tarball/master
Platform: UNKNOWN
Classifier: Development Status :: 5 - Production/Stable
Classifier: Environment :: Web Environment
Classifier: Framework :: Django
Classifier: Intended Audience :: Developers
Classifier: License :: OSI Approved :: MIT License
Classifier: Programming Language :: Python
Classifier: Programming Language :: Python :: 2.7
Classifier: Programming Language :: Python :: 3
Classifier: Programming Language :: Python :: 3.4
Classifier: Programming Language :: Python :: 3.5
Classifier: Programming Language :: Python :: 3.7
Classifier: Topic :: Software Development :: Libraries :: Python Modules
Classifier: Topic :: System :: Networking
